fasttlogparser/__init__.py
fasttlogparser/fasttlogparser.cp313-win_amd64.pyd
fasttlogparser-1.1.1.dist-info/METADATA
fasttlogparser-1.1.1.dist-info/WHEEL
fasttlogparser-1.1.1.dist-info/licenses/LICENSE
fasttlogparser-1.1.1.dist-info/RECORD
