Metadata-Version: 2.4
Name: fasttlogparser
Version: 1.1.1
Summary: Blazing-Fast MAVLink .tlog Parser
Author-Email: Anton Bogdanov <bogdan0v.am@yandex.ru>
License-Expression: MIT
License-File: LICENSE
Classifier: Programming Language :: Python :: 3
Classifier: Operating System :: OS Independent
Project-URL: Homepage, https://github.com/Bogdanov-am/fasttlogparser
Project-URL: Issues, https://github.com/Bogdanov-am/fasttlogparser/issues
Requires-Python: >=3.10
